osrs_hiscore/__init__.py
osrs_hiscore/cli.py
osrs_hiscore/core.py
runescape_hiscore-0.1.3.dist-info/licenses/LICENSE
runescape_hiscore-0.1.3.dist-info/METADATA
runescape_hiscore-0.1.3.dist-info/WHEEL
runescape_hiscore-0.1.3.dist-info/entry_points.txt
runescape_hiscore-0.1.3.dist-info/top_level.txt
runescape_hiscore-0.1.3.dist-info/RECORD
