Metadata-Version: 2.4
Name: runescape-hiscore
Version: 0.1.3
Summary: A CLI tool to fetch OldSchool RuneScape hiscores
Home-page: https://github.com/JustinDeanS/osrs-hiscore
Author: Justin Shields
Author-email: justinshields321@gmail.com
License: MIT
Classifier: Programming Language :: Python :: 3
Classifier: License :: OSI Approved :: MIT License
Classifier: Operating System :: OS Independent
License-File: LICENSE
Requires-Dist: requests>=2.0
Requires-Dist: rich>=10.0
Provides-Extra: test
Requires-Dist: pytest; extra == "test"
Requires-Dist: flake8; extra == "test"
Dynamic: license-file
